LICENSE
README.md
google_recaptcha_flask.py
setup.py
google_recaptcha_flask.egg-info/PKG-INFO
google_recaptcha_flask.egg-info/SOURCES.txt
google_recaptcha_flask.egg-info/dependency_links.txt
google_recaptcha_flask.egg-info/requires.txt
google_recaptcha_flask.egg-info/top_level.txt