Metadata-Version: 2.1
Name: google-recaptcha-flask
Version: 0.1.1
Summary: Exemplo de pacote PyPI
Home-page: https://github.com/brunolimasp/Flask-Google-reCaptcha
Author: Bruno Augusto
Author-email: augusto.han@gmail.com
License: MIT License
Keywords: flask,recaptcha,google
Platform: UNKNOWN
License-File: LICENSE
